iSearch/__init__.py
iSearch/isearch.py
iSearch-1.0.2.dist-info/DESCRIPTION.rst
iSearch-1.0.2.dist-info/LICENSE.txt
iSearch-1.0.2.dist-info/METADATA
iSearch-1.0.2.dist-info/RECORD
iSearch-1.0.2.dist-info/WHEEL
iSearch-1.0.2.dist-info/entry_points.txt
iSearch-1.0.2.dist-info/metadata.json
iSearch-1.0.2.dist-info/top_level.txt
