Metadata-Version: 2.0
Name: iSearch
Version: 1.0.2
Summary: 有道词典单词查询、存储和管理的命令行工具
Home-page: https://github.com/louisun/iSearch
Author: louisun
Author-email: luyang.sun@outlook.com
License: MIT
Keywords: dictionary,youdao,word
Platform: UNKNOWN
Classifier: Development Status :: 3 - Alpha
Classifier: Environment :: Web Environment
Classifier: Intended Audience :: Developers
Classifier: License :: OSI Approved :: MIT License
Classifier: Operating System :: OS Independent
Classifier: Programming Language :: Python
Classifier: Programming Language :: Python :: 2
Classifier: Programming Language :: Python :: 2.7
Classifier: Programming Language :: Python :: 3
Classifier: Programming Language :: Python :: 3.6
Classifier: Topic :: Internet :: WWW/HTTP
Classifier: Topic :: Software Development :: Libraries :: Python Modules
Requires-Dist: bs4
Requires-Dist: requests
Requires-Dist: termcolor
